ifc_utils/__init__.py
ifc_utils/ifcopenshell_utils.py
ifc_utils-0.0.5.dist-info/LICENSE
ifc_utils-0.0.5.dist-info/METADATA
ifc_utils-0.0.5.dist-info/WHEEL
ifc_utils-0.0.5.dist-info/top_level.txt
ifc_utils-0.0.5.dist-info/RECORD
